{"SeriazableComponent":"map","components":{"1":[{"c":"wkbl"},{"c":"pos","x":0,"y":0}],"2":[{"c":"wkbl"},{"c":"pos","x":0,"y":1},{"c":"start"}],"3":[{"c":"wkbl"},{"c":"pos","x":0,"y":2},{"c":"start"}],"4":[{"c":"wkbl"},{"c":"pos","x":0,"y":3}],"5":[{"c":"wkbl"},{"c":"pos","x":0,"y":4}],"6":[{"c":"wkbl"},{"c":"pos","x":0,"y":5},{"c":"start"}],"7":[{"c":"wkbl"},{"c":"pos","x":0,"y":10},{"c":"start"}],"8":[{"c":"wkbl"},{"c":"pos","x":0,"y":11},{"c":"start"}],"9":[{"c":"wkbl"},{"c":"pos","x":0,"y":12},{"c":"start"}],"10":[{"c":"wkbl"},{"c":"pos","x":0,"y":14}],"11":[{"c":"wkbl"},{"c":"pos","x":0,"y":15}],"12":[{"c":"wkbl"},{"c":"pos","x":1,"y":0},{"c":"start"}],"13":[{"c":"wkbl"},{"c":"pos","x":1,"y":1},{"c":"start"}],"14":[{"c":"wkbl"},{"c":"pos","x":1,"y":3}],"15":[{"c":"wkbl"},{"c":"pos","x":1,"y":4}],"16":[{"c":"wkbl"},{"c":"pos","x":1,"y":5}],"17":[{"c":"wkbl"},{"c":"pos","x":1,"y":6},{"c":"start"}],"18":[{"c":"wkbl"},{"c":"pos","x":1,"y":7},{"c":"start"}],"19":[{"c":"wkbl"},{"c":"pos","x":1,"y":8}],"20":[{"c":"wkbl"},{"c":"pos","x":1,"y":9}],"21":[{"c":"wkbl"},{"c":"pos","x":1,"y":10}],"22":[{"c":"wkbl"},{"c":"pos","x":1,"y":11}],"23":[{"c":"wkbl"},{"c":"pos","x":1,"y":12},{"c":"start"}],"24":[{"c":"wkbl"},{"c":"pos","x":1,"y":14}],"25":[{"c":"wkbl"},{"c":"pos","x":1,"y":15}],"26":[{"c":"wkbl"},{"c":"pos","x":2,"y":1},{"c":"start"}],"27":[{"c":"wkbl"},{"c":"pos","x":2,"y":3},{"c":"start"}],"28":[{"c":"wkbl"},{"c":"pos","x":2,"y":4},{"c":"start"}],"29":[{"c":"wkbl"},{"c":"pos","x":2,"y":5},{"c":"start"}],"30":[{"c":"wkbl"},{"c":"pos","x":2,"y":6}],"31":[{"c":"wkbl"},{"c":"pos","x":2,"y":7}],"32":[{"c":"wkbl"},{"c":"pos","x":2,"y":8}],"33":[{"c":"wkbl"},{"c":"pos","x":2,"y":9}],"34":[{"c":"wkbl"},{"c":"pos","x":2,"y":10}],"35":[{"c":"wkbl"},{"c":"pos","x":2,"y":11}],"36":[{"c":"wkbl"},{"c":"pos","x":2,"y":12}],"37":[{"c":"wkbl"},{"c":"pos","x":2,"y":13}],"38":[{"c":"wkbl"},{"c":"pos","x":2,"y":14}],"39":[{"c":"wkbl"},{"c":"pos","x":2,"y":15}],"40":[{"c":"wkbl"},{"c":"pos","x":3,"y":0}],"41":[{"c":"wkbl"},{"c":"pos","x":3,"y":1}],"42":[{"c":"wkbl"},{"c":"pos","x":3,"y":2}],"43":[{"c":"wkbl"},{"c":"pos","x":3,"y":3}],"44":[{"c":"wkbl"},{"c":"pos","x":3,"y":4}],"45":[{"c":"wkbl"},{"c":"pos","x":3,"y":5}],"46":[{"c":"wkbl"},{"c":"pos","x":3,"y":7}],"47":[{"c":"wkbl"},{"c":"pos","x":3,"y":8}],"48":[{"c":"wkbl"},{"c":"pos","x":3,"y":9}],"49":[{"c":"wkbl"},{"c":"pos","x":3,"y":10}],"50":[{"c":"wkbl"},{"c":"pos","x":3,"y":11}],"51":[{"c":"wkbl"},{"c":"pos","x":3,"y":12}],"52":[{"c":"wkbl"},{"c":"pos","x":3,"y":14}],"53":[{"c":"wkbl"},{"c":"pos","x":3,"y":15}],"54":[{"c":"wkbl"},{"c":"pos","x":4,"y":0}],"55":[{"c":"wkbl"},{"c":"pos","x":4,"y":1}],"56":[{"c":"wkbl"},{"c":"pos","x":4,"y":2}],"57":[{"c":"wkbl"},{"c":"pos","x":4,"y":3}],"58":[{"c":"wkbl"},{"c":"pos","x":4,"y":4}],"59":[{"c":"wkbl"},{"c":"pos","x":4,"y":5}],"60":[{"c":"wkbl"},{"c":"pos","x":4,"y":6}],"61":[{"c":"wkbl"},{"c":"pos","x":4,"y":7}],"62":[{"c":"wkbl"},{"c":"pos","x":4,"y":8}],"63":[{"c":"wkbl"},{"c":"pos","x":4,"y":9}],"64":[{"c":"wkbl"},{"c":"pos","x":4,"y":10}],"65":[{"c":"wkbl"},{"c":"pos","x":4,"y":11}],"66":[{"c":"wkbl"},{"c":"pos","x":4,"y":12}],"67":[{"c":"wkbl"},{"c":"pos","x":4,"y":13}],"68":[{"c":"wkbl"},{"c":"pos","x":4,"y":15}],"69":[{"c":"wkbl"},{"c":"pos","x":5,"y":0}],"70":[{"c":"wkbl"},{"c":"pos","x":5,"y":1}],"71":[{"c":"wkbl"},{"c":"pos","x":5,"y":2}],"72":[{"c":"wkbl"},{"c":"pos","x":5,"y":4}],"73":[{"c":"wkbl"},{"c":"pos","x":5,"y":7}],"74":[{"c":"wkbl"},{"c":"pos","x":5,"y":8}],"75":[{"c":"wkbl"},{"c":"pos","x":5,"y":9}],"76":[{"c":"wkbl"},{"c":"pos","x":5,"y":10}],"77":[{"c":"wkbl"},{"c":"pos","x":5,"y":11}],"78":[{"c":"wkbl"},{"c":"pos","x":5,"y":12}],"79":[{"c":"wkbl"},{"c":"pos","x":5,"y":14}],"80":[{"c":"wkbl"},{"c":"pos","x":5,"y":15}],"81":[{"c":"wkbl"},{"c":"pos","x":6,"y":0}],"82":[{"c":"wkbl"},{"c":"pos","x":6,"y":1}],"83":[{"c":"wkbl"},{"c":"pos","x":6,"y":2}],"84":[{"c":"wkbl"},{"c":"pos","x":6,"y":5}],"85":[{"c":"wkbl"},{"c":"pos","x":6,"y":6}],"86":[{"c":"wkbl"},{"c":"pos","x":6,"y":10}],"87":[{"c":"wkbl"},{"c":"pos","x":6,"y":11}],"88":[{"c":"wkbl"},{"c":"pos","x":6,"y":12}],"89":[{"c":"wkbl"},{"c":"pos","x":6,"y":14}],"90":[{"c":"wkbl"},{"c":"pos","x":6,"y":15}],"91":[{"c":"wkbl"},{"c":"pos","x":7,"y":2}],"92":[{"c":"wkbl"},{"c":"pos","x":7,"y":4}],"93":[{"c":"wkbl"},{"c":"pos","x":7,"y":5}],"94":[{"c":"wkbl"},{"c":"pos","x":7,"y":6}],"95":[{"c":"wkbl"},{"c":"pos","x":7,"y":8}],"96":[{"c":"wkbl"},{"c":"pos","x":7,"y":9}],"97":[{"c":"wkbl"},{"c":"pos","x":7,"y":10}],"98":[{"c":"wkbl"},{"c":"pos","x":7,"y":11}],"99":[{"c":"wkbl"},{"c":"pos","x":7,"y":12}],"100":[{"c":"wkbl"},{"c":"pos","x":7,"y":14}],"101":[{"c":"wkbl"},{"c":"pos","x":7,"y":15}],"102":[{"c":"wkbl"},{"c":"pos","x":8,"y":0}],"103":[{"c":"wkbl"},{"c":"pos","x":8,"y":1}],"104":[{"c":"wkbl"},{"c":"pos","x":8,"y":5}],"105":[{"c":"wkbl"},{"c":"pos","x":8,"y":6}],"106":[{"c":"wkbl"},{"c":"pos","x":8,"y":7}],"107":[{"c":"wkbl"},{"c":"pos","x":8,"y":8}],"108":[{"c":"wkbl"},{"c":"pos","x":8,"y":9}],"109":[{"c":"wkbl"},{"c":"pos","x":8,"y":10}],"110":[{"c":"wkbl"},{"c":"pos","x":8,"y":11}],"111":[{"c":"wkbl"},{"c":"pos","x":8,"y":12}],"112":[{"c":"wkbl"},{"c":"pos","x":8,"y":14}],"113":[{"c":"wkbl"},{"c":"pos","x":8,"y":15}],"114":[{"c":"wkbl"},{"c":"pos","x":9,"y":0}],"115":[{"c":"wkbl"},{"c":"pos","x":9,"y":1}],"116":[{"c":"wkbl"},{"c":"pos","x":9,"y":2}],"117":[{"c":"wkbl"},{"c":"pos","x":9,"y":3}],"118":[{"c":"wkbl"},{"c":"pos","x":9,"y":4}],"119":[{"c":"wkbl"},{"c":"pos","x":9,"y":5}],"120":[{"c":"wkbl"},{"c":"pos","x":9,"y":6}],"121":[{"c":"wkbl"},{"c":"pos","x":9,"y":7}],"122":[{"c":"wkbl"},{"c":"pos","x":9,"y":8}],"123":[{"c":"wkbl"},{"c":"pos","x":9,"y":11}],"124":[{"c":"wkbl"},{"c":"pos","x":9,"y":12}],"125":[{"c":"wkbl"},{"c":"pos","x":9,"y":14}],"126":[{"c":"wkbl"},{"c":"pos","x":9,"y":15}],"127":[{"c":"wkbl"},{"c":"pos","x":10,"y":0}],"128":[{"c":"wkbl"},{"c":"pos","x":10,"y":1}],"129":[{"c":"wkbl"},{"c":"pos","x":10,"y":2}],"130":[{"c":"wkbl"},{"c":"pos","x":10,"y":3}],"131":[{"c":"wkbl"},{"c":"pos","x":10,"y":5}],"132":[{"c":"wkbl"},{"c":"pos","x":10,"y":6}],"133":[{"c":"wkbl"},{"c":"pos","x":10,"y":8}],"134":[{"c":"wkbl"},{"c":"pos","x":10,"y":9}],"135":[{"c":"wkbl"},{"c":"pos","x":10,"y":11}],"136":[{"c":"wkbl"},{"c":"pos","x":10,"y":12}],"137":[{"c":"wkbl"},{"c":"pos","x":10,"y":13}],"138":[{"c":"wkbl"},{"c":"pos","x":10,"y":14}],"139":[{"c":"wkbl"},{"c":"pos","x":10,"y":15}],"140":[{"c":"wkbl"},{"c":"pos","x":11,"y":0}],"141":[{"c":"wkbl"},{"c":"pos","x":11,"y":1}],"142":[{"c":"wkbl"},{"c":"pos","x":11,"y":2}],"143":[{"c":"wkbl"},{"c":"pos","x":11,"y":4}],"144":[{"c":"wkbl"},{"c":"pos","x":11,"y":5}],"145":[{"c":"wkbl"},{"c":"pos","x":11,"y":6}],"146":[{"c":"wkbl"},{"c":"pos","x":11,"y":7}],"147":[{"c":"wkbl"},{"c":"pos","x":11,"y":8}],"148":[{"c":"wkbl"},{"c":"pos","x":11,"y":9}],"149":[{"c":"wkbl"},{"c":"pos","x":11,"y":10}],"150":[{"c":"wkbl"},{"c":"pos","x":11,"y":11}],"151":[{"c":"wkbl"},{"c":"pos","x":11,"y":12}],"152":[{"c":"wkbl"},{"c":"pos","x":11,"y":13}],"153":[{"c":"wkbl"},{"c":"pos","x":11,"y":14}],"154":[{"c":"wkbl"},{"c":"pos","x":11,"y":15}],"155":[{"c":"wkbl"},{"c":"pos","x":12,"y":0}],"156":[{"c":"wkbl"},{"c":"pos","x":12,"y":1}],"157":[{"c":"wkbl"},{"c":"pos","x":12,"y":2}],"158":[{"c":"wkbl"},{"c":"pos","x":12,"y":5}],"159":[{"c":"wkbl"},{"c":"pos","x":12,"y":6}],"160":[{"c":"wkbl"},{"c":"pos","x":12,"y":7}],"161":[{"c":"wkbl"},{"c":"pos","x":12,"y":8}],"162":[{"c":"wkbl"},{"c":"pos","x":12,"y":11}],"163":[{"c":"wkbl"},{"c":"pos","x":12,"y":12}],"164":[{"c":"wkbl"},{"c":"pos","x":12,"y":13}],"165":[{"c":"wkbl"},{"c":"pos","x":12,"y":14}],"166":[{"c":"wkbl"},{"c":"pos","x":12,"y":15}],"167":[{"c":"wkbl"},{"c":"pos","x":13,"y":0}],"168":[{"c":"wkbl"},{"c":"pos","x":13,"y":1}],"169":[{"c":"wkbl"},{"c":"pos","x":13,"y":2}],"170":[{"c":"wkbl"},{"c":"pos","x":13,"y":3}],"171":[{"c":"wkbl"},{"c":"pos","x":13,"y":4}],"172":[{"c":"wkbl"},{"c":"pos","x":13,"y":5}],"173":[{"c":"wkbl"},{"c":"pos","x":13,"y":6}],"174":[{"c":"wkbl"},{"c":"pos","x":13,"y":7}],"175":[{"c":"wkbl"},{"c":"pos","x":13,"y":9}],"176":[{"c":"wkbl"},{"c":"pos","x":13,"y":11}],"177":[{"c":"wkbl"},{"c":"pos","x":13,"y":12}],"178":[{"c":"wkbl"},{"c":"pos","x":13,"y":13}],"179":[{"c":"wkbl"},{"c":"pos","x":13,"y":15}],"180":[{"c":"wkbl"},{"c":"pos","x":14,"y":0}],"181":[{"c":"wkbl"},{"c":"pos","x":14,"y":2}],"182":[{"c":"wkbl"},{"c":"pos","x":14,"y":4}],"183":[{"c":"wkbl"},{"c":"pos","x":14,"y":5}],"184":[{"c":"wkbl"},{"c":"pos","x":14,"y":6}],"185":[{"c":"wkbl"},{"c":"pos","x":14,"y":7}],"186":[{"c":"wkbl"},{"c":"pos","x":14,"y":8}],"187":[{"c":"wkbl"},{"c":"pos","x":14,"y":9}],"188":[{"c":"wkbl"},{"c":"pos","x":14,"y":10}],"189":[{"c":"wkbl"},{"c":"pos","x":14,"y":11}],"190":[{"c":"wkbl"},{"c":"pos","x":14,"y":12}],"191":[{"c":"wkbl"},{"c":"pos","x":14,"y":13}],"192":[{"c":"wkbl"},{"c":"pos","x":14,"y":14}],"193":[{"c":"wkbl"},{"c":"pos","x":14,"y":15}],"194":[{"c":"wkbl"},{"c":"pos","x":15,"y":0}],"195":[{"c":"wkbl"},{"c":"pos","x":15,"y":1}],"196":[{"c":"wkbl"},{"c":"pos","x":15,"y":3}],"197":[{"c":"wkbl"},{"c":"pos","x":15,"y":4}],"198":[{"c":"wkbl"},{"c":"pos","x":15,"y":5}],"199":[{"c":"wkbl"},{"c":"pos","x":15,"y":6}],"200":[{"c":"wkbl"},{"c":"pos","x":15,"y":7}],"201":[{"c":"wkbl"},{"c":"pos","x":15,"y":8}],"202":[{"c":"wkbl"},{"c":"pos","x":15,"y":9}],"203":[{"c":"wkbl"},{"c":"pos","x":15,"y":10}],"204":[{"c":"wkbl"},{"c":"pos","x":15,"y":11}],"205":[{"c":"wkbl"},{"c":"pos","x":15,"y":14}],"206":[{"c":"pos","x":0,"y":0},{"c":"tree"},{"c":"osbl"}],"207":[{"c":"pos","x":1,"y":9},{"c":"tree"},{"c":"osbl"}],"208":[{"c":"pos","x":2,"y":6},{"c":"tree"},{"c":"osbl"}],"209":[{"c":"pos","x":2,"y":7},{"c":"tree"},{"c":"osbl"}],"210":[{"c":"pos","x":2,"y":8},{"c":"tree"},{"c":"osbl"}],"211":[{"c":"pos","x":2,"y":10},{"c":"tree"},{"c":"osbl"}],"212":[{"c":"pos","x":2,"y":13},{"c":"tree"},{"c":"osbl"}],"213":[{"c":"pos","x":2,"y":14},{"c":"tree"},{"c":"osbl"}],"214":[{"c":"pos","x":3,"y":3},{"c":"tree"},{"c":"osbl"}],"215":[{"c":"pos","x":3,"y":4},{"c":"tree"},{"c":"osbl"}],"216":[{"c":"pos","x":3,"y":12},{"c":"tree"},{"c":"osbl"}],"217":[{"c":"pos","x":3,"y":14},{"c":"tree"},{"c":"osbl"}],"218":[{"c":"pos","x":4,"y":3},{"c":"tree"},{"c":"osbl"}],"219":[{"c":"pos","x":4,"y":10},{"c":"tree"},{"c":"osbl"}],"220":[{"c":"pos","x":4,"y":12},{"c":"tree"},{"c":"osbl"}],"221":[{"c":"pos","x":4,"y":13},{"c":"tree"},{"c":"osbl"}],"222":[{"c":"pos","x":5,"y":4},{"c":"tree"},{"c":"osbl"}],"223":[{"c":"pos","x":6,"y":11},{"c":"tree"},{"c":"osbl"}],"224":[{"c":"pos","x":6,"y":12},{"c":"tree"},{"c":"osbl"}],"225":[{"c":"pos","x":7,"y":6},{"c":"tree"},{"c":"osbl"}],"226":[{"c":"pos","x":8,"y":8},{"c":"tree"},{"c":"osbl"}],"227":[{"c":"pos","x":8,"y":11},{"c":"tree"},{"c":"osbl"}],"228":[{"c":"pos","x":9,"y":2},{"c":"tree"},{"c":"osbl"}],"229":[{"c":"pos","x":9,"y":6},{"c":"tree"},{"c":"osbl"}],"230":[{"c":"pos","x":9,"y":11},{"c":"tree"},{"c":"osbl"}],"231":[{"c":"pos","x":10,"y":0},{"c":"tree"},{"c":"osbl"}],"232":[{"c":"pos","x":10,"y":12},{"c":"tree"},{"c":"osbl"}],"233":[{"c":"pos","x":11,"y":4},{"c":"tree"},{"c":"osbl"}],"234":[{"c":"pos","x":11,"y":6},{"c":"tree"},{"c":"osbl"}],"235":[{"c":"pos","x":11,"y":14},{"c":"tree"},{"c":"osbl"}],"236":[{"c":"pos","x":12,"y":0},{"c":"tree"},{"c":"osbl"}],"237":[{"c":"pos","x":12,"y":8},{"c":"tree"},{"c":"osbl"}],"238":[{"c":"pos","x":12,"y":14},{"c":"tree"},{"c":"osbl"}],"239":[{"c":"pos","x":15,"y":3},{"c":"tree"},{"c":"osbl"}],"240":[{"c":"pos","x":15,"y":7},{"c":"tree"},{"c":"osbl"}],"241":[{"c":"pos","x":15,"y":9},{"c":"tree"},{"c":"osbl"}],"242":[{"c":"pos","x":15,"y":14},{"c":"tree"},{"c":"osbl"}]}}